cowpatch/__init__.py
cowpatch/base_elements.py
cowpatch/config.py
cowpatch/exceptions.py
cowpatch/layout_elements.py
cowpatch/svg_utils.py
cowpatch/text_elements.py
cowpatch/utils.py
cowpatch/wrappers.py
cowpatch-0.1.2.dist-info/LICENSE
cowpatch-0.1.2.dist-info/WHEEL
cowpatch-0.1.2.dist-info/METADATA
cowpatch-0.1.2.dist-info/RECORD
