Metadata-Version: 2.1
Name: cowpatch
Version: 0.1.2
Summary: A package for combining python ggplot visuals
Home-page: https://benjaminleroy.github.io/cowpatch/
License: MIT
Author: Benjamin LeRoy
Requires-Python: >=3.8,<4.0
Classifier: License :: OSI Approved :: MIT License
Classifier: Programming Language :: Python :: 3
Classifier: Programming Language :: Python :: 3.8
Classifier: Programming Language :: Python :: 3.9
Classifier: Programming Language :: Python :: 3.10
Classifier: Programming Language :: Python :: 3.11
Requires-Dist: CairoSVG (>=2.5.2,<3.0.0)
Requires-Dist: ipython (>=8.0.1,<9.0.0)
Requires-Dist: matplotlib (>=3.5.1,<4.0.0)
Requires-Dist: numpy (>=1.21.4,<2.0.0)
Requires-Dist: plotnine (>=0.10.0,<0.11.0)
Requires-Dist: svgutils (>=0.3.4,<0.4.0)
Project-URL: Repository, https://github.com/benjaminleroy/cowpatch/
